Adam_tanhx/Adam_tanhx.py
Adam_tanhx/__init__.py
Adam_tanhx-0.0.5.dist-info/LICENSE
Adam_tanhx-0.0.5.dist-info/METADATA
Adam_tanhx-0.0.5.dist-info/WHEEL
Adam_tanhx-0.0.5.dist-info/top_level.txt
Adam_tanhx-0.0.5.dist-info/RECORD
